LICENSE.txt
MANIFEST.in
README.md
README.rst
setup.py
colloquial/__init__.py
colloquial/_version.py
colloquial/colloquialisms/__init__.py
colloquial/colloquialisms/admin.py
colloquial/colloquialisms/admin_views.py
colloquial/colloquialisms/apps.py
colloquial/colloquialisms/models.py
colloquial/colloquialisms/parser.py
colloquial/colloquialisms/querysets.py
colloquial/colloquialisms/views.py
colloquial/colloquialisms/migrations/0001_initial.py
colloquial/colloquialisms/migrations/__init__.py
colloquial/colloquialisms/templates/.DS_Store
colloquial/colloquialisms/templates/admin/.DS_Store
colloquial/colloquialisms/templates/admin/colloquial/.DS_Store
colloquial/colloquialisms/templates/admin/colloquial/process_transcript.html
colloquial/colloquialisms/templates/admin/colloquial/tag_transcript.html
colloquial/colloquialisms/tests/__init__.py
colloquial/colloquialisms/tests/test_models.py
colloquial/colloquialisms/tests/test_parser.py
colloquial/transcripts/__init__.py
colloquial/transcripts/admin.py
colloquial/transcripts/apps.py
colloquial/transcripts/models.py
colloquial/transcripts/urls.py
colloquial/transcripts/migrations/0001_initial.py
colloquial/transcripts/migrations/__init__.py
django_colloquial.egg-info/PKG-INFO
django_colloquial.egg-info/SOURCES.txt
django_colloquial.egg-info/dependency_links.txt
django_colloquial.egg-info/not-zip-safe
django_colloquial.egg-info/requires.txt
django_colloquial.egg-info/top_level.txt